Workbook

Sheet Orders
A1: Order ID | B1: Order Date | C1: Year | D1: Month | E1: Customer | F1: Country | G1: Product | H1: Category | I1: Quantity | J1: Sales
A2: O0001 | B2: 46039 | C2: 2026 | D2: Jan | E2: Amara Otieno | F2: Kenya | G2: iPhone 16 | H2: Smartphone | I2: 1 | J2: 1000
A3: O0002 | B3: 45991 | C3: 2025 | D3: Nov | E3: Chipo Marufu | F3: Zimbabwe | G3: Bluetooth Headphones | H3: Accessory | I3: 1 | J3: 120
A4: O0003 | B4: 45481 | C4: 2024 | D4: Jul | E4: Tendai Moyo | F4: Zimbabwe | G4: Dell XPS 15 | H4: Laptop | I4: 2 | J4: 3000
A5: O0004 | B5: 46249 | C5: 2026 | D5: Aug | E5: Kudzai Sibanda | F5: Zimbabwe | G5: ThinkPad X1 | H5: Laptop | I5: 1 | J5: 1400
A6: O0005 | B6: 46123 | C6: 2026 | D6: Apr | E6: Chipo Marufu | F6: Zimbabwe | G6: OnePlus 13 | H6: Smartphone | I6: 1 | J6: 600
A7: O0006 | B7: 45938 | C7: 2025 | D7: Oct | E7: Amara Otieno | F7: Kenya | G7: Galaxy S24 | H7: Smartphone | I7: 2 | J7: 1600
A8: O0007 | B8: 45458 | C8: 2024 | D8: Jun | E8: Chanda Phiri | F8: Zambia | G8: Echo Dot 6 | H8: Smart Home | I8: 3 | J8: 300
A9: O0008 | B9: 45533 | C9: 2024 | D9: Aug | E9: Chanda Phiri | F9: Zambia | G9: MacBook Air M4 | H9: Laptop | I9: 1 | J9: 1000
A10: O0009 | B10: 45856 | C10: 2025 | D10: Jul | E10: Chipo Marufu | F10: Zimbabwe | G10: Surface Go 4 | H10: Tablet | I10: 1 | J10: 600
A11: O0010 | B11: 45383 | C11: 2024 | D11: Apr | E11: Nyasha Banda | F11: Zimbabwe | G11: HP Spectre x360 | H11: Laptop | I11: 1 | J11: 1200
A12: O0011 | B12: 46317 | C12: 2026 | D12: Oct | E12: Kudzai Sibanda | F12: Zimbabwe | G12: ThinkPad X1 | H12: Laptop | I12: 1 | J12: 1400
A13: O0012 | B13: 45857 | C13: 2025 | D13: Jul | E13: Tendai Moyo | F13: Zimbabwe | G13: Surface Go 4 | H13: Tablet | I13: 1 | J13: 600
... A101: O0100 | B101: 46288 | C101: 2026 | D101: Sep | E101: Thabo Nkosi | F101: South Africa | G101: Bluetooth Headphones | H101: Accessory | I101: 1 | J101: 120

Sheet Pivot Result
A1: What your PivotTable should show: Total Sales by Category and Year
A2: Built here with SUMIFS rather than a real PivotTable, so you can see the logic. A PivotTable does exactly this - it just does it by dragging instead of typing.
A4: Category | B4: 2024 | C4: 2025 | D4: 2026 | E4: Grand Total
A5: Laptop | B5: =SUMIFS(Orders!$J$2:$J$101,Orders!$H$2:$H$101,$A5,Orders!$C$2:$C$101,2024) | C5: =SUMIFS(Orders!$J$2:$J$101,Orders!$H$2:$H$101,$A5,Orders!$C$2:$C$101,2025) | D5: =SUMIFS(Orders!$J$2:$J$101,Orders!$H$2:$H$101,$A5,Orders!$C$2:$C$101,2026) | E5: =SUM(B5:D5)
A6: Smartphone | B6: =SUMIFS(Orders!$J$2:$J$101,Orders!$H$2:$H$101,$A6,Orders!$C$2:$C$101,2024) | C6: =SUMIFS(Orders!$J$2:$J$101,Orders!$H$2:$H$101,$A6,Orders!$C$2:$C$101,2025) | D6: =SUMIFS(Orders!$J$2:$J$101,Orders!$H$2:$H$101,$A6,Orders!$C$2:$C$101,2026) | E6: =SUM(B6:D6)
A7: Tablet | B7: =SUMIFS(Orders!$J$2:$J$101,Orders!$H$2:$H$101,$A7,Orders!$C$2:$C$101,2024) | C7: =SUMIFS(Orders!$J$2:$J$101,Orders!$H$2:$H$101,$A7,Orders!$C$2:$C$101,2025) | D7: =SUMIFS(Orders!$J$2:$J$101,Orders!$H$2:$H$101,$A7,Orders!$C$2:$C$101,2026) | E7: =SUM(B7:D7)
A8: Accessory | B8: =SUMIFS(Orders!$J$2:$J$101,Orders!$H$2:$H$101,$A8,Orders!$C$2:$C$101,2024) | C8: =SUMIFS(Orders!$J$2:$J$101,Orders!$H$2:$H$101,$A8,Orders!$C$2:$C$101,2025) | D8: =SUMIFS(Orders!$J$2:$J$101,Orders!$H$2:$H$101,$A8,Orders!$C$2:$C$101,2026) | E8: =SUM(B8:D8)
A9: Smart Home | B9: =SUMIFS(Orders!$J$2:$J$101,Orders!$H$2:$H$101,$A9,Orders!$C$2:$C$101,2024) | C9: =SUMIFS(Orders!$J$2:$J$101,Orders!$H$2:$H$101,$A9,Orders!$C$2:$C$101,2025) | D9: =SUMIFS(Orders!$J$2:$J$101,Orders!$H$2:$H$101,$A9,Orders!$C$2:$C$101,2026) | E9: =SUM(B9:D9)
A10: Grand Total | B10: =SUM(B5:B9) | C10: =SUM(C5:C9) | D10: =SUM(D5:D9) | E10: =SUM(E5:E9)

Sheet What-If
A1: NovaTech Retail - Next Year Projection
A3: INPUTS (change the yellow cells)
A4: Current Annual Revenue | B4: =SUM(Orders!J2:J101) | D4: Goal Seek target for Step 12: set B13 to 16000 by changing B5 (answer is about 10%).
A5: Price Increase | B5: 0 | D5: Note the results depend on each other: Revenue feeds Costs, both feed Profit.
A6: Expected Volume Change | B6: -0.02
A7: Cost as % of Revenue | B7: 0.62
A8: Fixed Costs | B8: 25000
A10: RESULTS (calculated - do not type over these)
A11: Projected Revenue | B11: =B4*(1+B5)*(1+B6)
A12: Projected Costs | B12: =B11*B7+B8
A13: Projected Profit | B13: =B11-B12
A14: Profit Margin | B14: =IFERROR(B13/B11,0)
